wagtailaudioembed/__init__.py
wagtailaudioembed/apps.py
wagtailaudioembed/embed.py
wagtailaudioembed/templates/wagtailaudioembed/audio.html
wagtail_audio_embed-0.1.2.dist-info/LICENSE
wagtail_audio_embed-0.1.2.dist-info/METADATA
wagtail_audio_embed-0.1.2.dist-info/WHEEL
wagtail_audio_embed-0.1.2.dist-info/top_level.txt
wagtail_audio_embed-0.1.2.dist-info/RECORD
