Metadata-Version: 2.1
Name: wagtail-audio-embed
Version: 0.1.2
Summary: (Allows using audio URLs in Wagtail-Embeds and render them using the <audio>-Tag)
Home-page: https://github.com/peterjochum/wagtail-audio-embed
Author: Peter Jochum
Author-email: peter.jochum@gmail.com
License: GPLv3,
Keywords: wagtail audio
Platform: UNKNOWN
Classifier: Development Status :: 3 - Alpha
Classifier: Framework :: Django
Classifier: Framework :: Django :: 3.2
Classifier: Framework :: Django :: 4.0
Classifier: Framework :: Wagtail
Classifier: Environment :: Web Environment
Classifier: Intended Audience :: Developers
Classifier: License :: OSI Approved :: GNU General Public License v3 or later (GPLv3+)
Classifier: Programming Language :: Python :: 3
Classifier: Programming Language :: Python :: 3.7
Classifier: Programming Language :: Python :: 3.8
Classifier: Programming Language :: Python :: 3.9
Classifier: Programming Language :: Python :: 3.10
Requires-Python: >=3.8
License-File: LICENSE
Requires-Dist: wagtail (>=2.13)
